chaco/__init__.py
chaco/_cython_speedups.c
chaco/_cython_speedups.cp314t-win32.pyd
chaco/_cython_speedups.pyx
chaco/_isnan.h
chaco/_speedups_fallback.py
chaco/_version.py
chaco/abstract_colormap.py
chaco/abstract_controller.py
chaco/abstract_data_range.py
chaco/abstract_data_source.py
chaco/abstract_mapper.py
chaco/abstract_overlay.py
chaco/abstract_plot_data.py
chaco/abstract_plot_renderer.py
chaco/api.py
chaco/array_data_source.py
chaco/array_plot_data.py
chaco/axis.py
chaco/axis_view.py
chaco/base.py
chaco/base_1d_mapper.py
chaco/base_1d_plot.py
chaco/base_2d_plot.py
chaco/base_candle_plot.py
chaco/base_contour_plot.py
chaco/base_data_range.py
chaco/base_plot_container.py
chaco/base_xy_plot.py
chaco/chaco_traits.py
chaco/color_mapper.py
chaco/color_spaces.py
chaco/colormap_generators.py
chaco/data_frame_plot_data.py
chaco/data_range_1d.py
chaco/data_range_2d.py
chaco/data_view.py
chaco/default_colormaps.py
chaco/default_colors.py
chaco/discrete_color_mapper.py
chaco/example_support.py
chaco/function_data_source.py
chaco/function_image_data.py
chaco/grid.py
chaco/grid_data_source.py
chaco/grid_mapper.py
chaco/image_data.py
chaco/image_utils.py
chaco/label.py
chaco/label_axis.py
chaco/linear_mapper.py
chaco/log_mapper.py
chaco/multi_array_data_source.py
chaco/pdf_graphics_context.py
chaco/plot.py
chaco/plot_canvas.py
chaco/plot_canvas_toolbar.py
chaco/plot_component.py
chaco/plot_containers.py
chaco/plot_factory.py
chaco/plot_graphics_context.py
chaco/plotscrollbar.py
chaco/point_data_source.py
chaco/polar_mapper.py
chaco/scales_tick_generator.py
chaco/scaly_plot.py
chaco/selectable_legend.py
chaco/speedups.py
chaco/svg_graphics_context.py
chaco/ticks.py
chaco/toolbar_plot.py
chaco/transform_color_mapper.py
chaco/downsample/__init__.py
chaco/downsample/_lttb.c
chaco/downsample/_lttb.cp314t-win32.pyd
chaco/downsample/_lttb.pyx
chaco/downsample/lttb.py
chaco/downsample/tests/__init__.py
chaco/downsample/tests/test_lttb.py
chaco/examples/__init__.py
chaco-6.1.1.dist-info/licenses/LICENSE.txt
chaco-6.1.1.dist-info/METADATA
chaco-6.1.1.dist-info/WHEEL
chaco-6.1.1.dist-info/entry_points.txt
chaco-6.1.1.dist-info/top_level.txt
chaco-6.1.1.dist-info/RECORD
