Metadata-Version: 2.4
Name: chaco
Version: 6.1.1
Summary: interactive 2-dimensional plotting
Home-page: http://docs.enthought.com/chaco
Download-URL: https://github.com/enthought/chaco
Author: Peter Wang, et. al.
Author-email: info@enthought.com
Maintainer: ETS Developers
Maintainer-email: enthought-dev@enthought.com
License: BSD
Platform: Windows
Platform: Linux
Platform: Mac OS-X
Platform: Unix
Platform: Solaris
Classifier: Development Status :: 5 - Production/Stable
Classifier: Intended Audience :: Developers
Classifier: Intended Audience :: Science/Research
Classifier: License :: OSI Approved :: BSD License
Classifier: Operating System :: MacOS
Classifier: Operating System :: Microsoft :: Windows
Classifier: Operating System :: OS Independent
Classifier: Operating System :: POSIX
Classifier: Operating System :: Unix
Classifier: Programming Language :: C
Classifier: Programming Language :: Python
Classifier: Topic :: Scientific/Engineering
Classifier: Topic :: Software Development
Classifier: Topic :: Software Development :: Libraries
Requires-Python: >=3.10
License-File: LICENSE.txt
Requires-Dist: traits>=6.2.0
Requires-Dist: traitsui
Requires-Dist: pyface>=7.2.0
Requires-Dist: numpy
Requires-Dist: enable[layout,svg]>=5.2.0
Provides-Extra: docs
Requires-Dist: enthought-sphinx-theme; extra == "docs"
Requires-Dist: sphinx; extra == "docs"
Requires-Dist: sphinx-copybutton; extra == "docs"
Provides-Extra: examples
Requires-Dist: encore; extra == "examples"
Requires-Dist: importlib_resources; python_version < "3.9" and extra == "examples"
Requires-Dist: scipy; extra == "examples"
Requires-Dist: pandas; extra == "examples"
Provides-Extra: tests
Requires-Dist: pandas; extra == "tests"
Provides-Extra: pyside2
Requires-Dist: enable[pyside2]; extra == "pyside2"
Provides-Extra: pyside6
Requires-Dist: enable[pyside6]; extra == "pyside6"
Provides-Extra: pyqt5
Requires-Dist: enable[pyqt5]; extra == "pyqt5"
Provides-Extra: pyqt6
Requires-Dist: enable[pyqt6]; extra == "pyqt6"
Provides-Extra: wx
Requires-Dist: enable[wx]; extra == "wx"
Provides-Extra: null
Dynamic: author
Dynamic: author-email
Dynamic: classifier
Dynamic: description
Dynamic: description-content-type
Dynamic: download-url
Dynamic: home-page
Dynamic: license
Dynamic: license-file
Dynamic: maintainer
Dynamic: maintainer-email
Dynamic: platform
Dynamic: provides-extra
Dynamic: requires-dist
Dynamic: requires-python
Dynamic: summary
